nysol/__init__.py
nysol/_nysolshell_core.cpython-38-x86_64-linux-gnu.so
nysol/shell.py
nysol/mcmd/__init__.py
nysol/mcmd/nysollib/__init__.py
nysol/mcmd/nysollib/core.py
nysol/mcmd/nysollib/draw.py
nysol/mcmd/nysollib/dspalign.py
nysol/mcmd/nysollib/itermod.py
nysol/mcmd/nysollib/nysolutil.py
nysol/mcmd/submod/__init__.py
nysol/mcmd/submod/cmd.py
nysol/mcmd/submod/list2csv.py
nysol/mcmd/submod/m2cat.py
nysol/mcmd/submod/m2cross.py
nysol/mcmd/submod/m2tee.py
nysol/mcmd/submod/maccum.py
nysol/mcmd/submod/marff2csv.py
nysol/mcmd/submod/mavg.py
nysol/mcmd/submod/mbest.py
nysol/mcmd/submod/mbucket.py
nysol/mcmd/submod/mcal.py
nysol/mcmd/submod/mcat.py
nysol/mcmd/submod/mchgnum.py
nysol/mcmd/submod/mchgstr.py
nysol/mcmd/submod/mcombi.py
nysol/mcmd/submod/mcommon.py
nysol/mcmd/submod/mcount.py
nysol/mcmd/submod/mcross.py
nysol/mcmd/submod/mcut.py
nysol/mcmd/submod/mdelnull.py
nysol/mcmd/submod/mdformat.py
nysol/mcmd/submod/mduprec.py
nysol/mcmd/submod/mfifo.py
nysol/mcmd/submod/mfldname.py
nysol/mcmd/submod/mfsort.py
nysol/mcmd/submod/mhashavg.py
nysol/mcmd/submod/mhashsum.py
nysol/mcmd/submod/mjoin.py
nysol/mcmd/submod/mkeybreak.py
nysol/mcmd/submod/mkmeans.py
nysol/mcmd/submod/mmbucket.py
nysol/mcmd/submod/mmvavg.py
nysol/mcmd/submod/mmvsim.py
nysol/mcmd/submod/mmvstats.py
nysol/mcmd/submod/mnewnumber.py
nysol/mcmd/submod/mnewrand.py
nysol/mcmd/submod/mnewstr.py
nysol/mcmd/submod/mnjoin.py
nysol/mcmd/submod/mnormalize.py
nysol/mcmd/submod/mnrcommon.py
nysol/mcmd/submod/mnrjoin.py
nysol/mcmd/submod/mnullto.py
nysol/mcmd/submod/mnumber.py
nysol/mcmd/submod/mpadding.py
nysol/mcmd/submod/mpaste.py
nysol/mcmd/submod/mproduct.py
nysol/mcmd/submod/mrand.py
nysol/mcmd/submod/mread.py
nysol/mcmd/submod/mrjoin.py
nysol/mcmd/submod/msed.py
nysol/mcmd/submod/msel.py
nysol/mcmd/submod/mselnum.py
nysol/mcmd/submod/mselrand.py
nysol/mcmd/submod/mselstr.py
nysol/mcmd/submod/msep.py
nysol/mcmd/submod/msetstr.py
nysol/mcmd/submod/mshare.py
nysol/mcmd/submod/mshuffle.py
nysol-0.3.16.dist-info/METADATA
nysol-0.3.16.dist-info/WHEEL
nysol-0.3.16.dist-info/top_level.txt
nysol-0.3.16.dist-info/RECORD
