Metadata-Version: 2.1
Name: nysol
Version: 0.3.16
Summary: This is nysol tools
Home-page: http://www.nysol.jp/
Author: nysol
Author-email: info@nysol.jp
License: AGPL3
Platform: UNKNOWN
Classifier: Development Status :: 4 - Beta
Classifier: Intended Audience :: Developers
Classifier: License :: OSI Approved :: GNU Affero General Public License v3
Classifier: Operating System :: POSIX :: Linux
Classifier: Operating System :: MacOS :: MacOS X
Classifier: Programming Language :: C
Classifier: Programming Language :: C++
Classifier: Programming Language :: Python :: 3
Classifier: Topic :: Software Development :: Libraries :: Python Modules
Classifier: Topic :: Scientific/Engineering :: Information Analysis
Classifier: Topic :: Scientific/Engineering :: Mathematics
Requires-Dist: psutil
